george_agent_package/__init__.py
george_agent_package/tools/__init__.py
george_agent_package/tools/agent_tool.py
george_agent_package/tools/math_tool_adapter.py
george_agent_package/tools/mir_tool_adapter.py
george_agent_package/tools/serp_tool_adapter.py
george_agent_package/tools/utils.py
george_agent_package/yamls/agent_tool.yaml
george_agent_package/yamls/math_tool.yaml
george_agent_package/yamls/mir_tool.yaml
george_agent_package/yamls/serp_tool.yaml
george_agent_package-0.0.5.dist-info/METADATA
george_agent_package-0.0.5.dist-info/WHEEL
george_agent_package-0.0.5.dist-info/entry_points.txt
george_agent_package-0.0.5.dist-info/top_level.txt
george_agent_package-0.0.5.dist-info/RECORD
