Metadata-Version: 2.1
Name: george-agent-package
Version: 0.0.5
Summary: This is my agent tools package
